{
  "profile": {
    "id": 2629,
    "name": "Melissa Mullins",
    "nickname": "No Mess",
    "photo": "https://media.api-sports.io/mma/fighters/2629.png",
    "gender": "W",
    "birth_date": null,
    "age": null,
    "height": "5' 7'",
    "weight": "137 lbs",
    "reach": "68'",
    "stance": "Orthodox",
    "category": "Women's Bantamweight",
    "team": {
      "id": 112,
      "name": "Renegade MMA"
    },
    "last_update": "2025-06-28T12:03:38+00:00"
  },
  "fights": [],
  "cachedAt": "2025-11-27T15:07:21.838Z"
}