{
  "profile": {
    "id": 555,
    "name": "Pannie Kianzad",
    "nickname": "Banzai",
    "photo": "https://media.api-sports.io/mma/fighters/555.png",
    "gender": "W",
    "birth_date": null,
    "age": null,
    "height": "5' 7'",
    "weight": "135 lbs",
    "reach": "66'",
    "stance": "Orthodox",
    "category": "Women's Bantamweight",
    "team": {
      "id": 31,
      "name": "Xtreme Couture"
    },
    "last_update": "2025-06-04T17:48:05+00:00"
  },
  "records": {
    "fighter": {
      "id": 555,
      "name": "Pannie Kianzad",
      "photo": "https://media.api-sports.io/mma/fighters/555.png"
    },
    "total": {
      "win": 17,
      "loss": 9,
      "draw": 0
    },
    "ko": {
      "win": 3,
      "loss": 1
    },
    "sub": {
      "win": 0,
      "loss": 3
    }
  },
  "fights": [],
  "cachedAt": "2025-11-27T15:07:16.619Z"
}